pyinfra_docker/__init__.py
pyinfra_docker/docker.py
pyinfra_docker-2.1.dist-info/LICENSE.md
pyinfra_docker-2.1.dist-info/METADATA
pyinfra_docker-2.1.dist-info/WHEEL
pyinfra_docker-2.1.dist-info/top_level.txt
pyinfra_docker-2.1.dist-info/RECORD
