Metadata-Version: 2.1
Name: pyinfra-docker
Version: 2.1
Summary: Install & configure Docker with `pyinfra`.
Home-page: https://github.com/Fizzadar/pyinfra-docker
Author: Nick / Fizzadar
Author-email: nick@fizzadar.com
License: MIT
Platform: UNKNOWN
License-File: LICENSE.md
Requires-Dist: pyinfra (<3,>=2)
Provides-Extra: lint
Requires-Dist: black ; extra == 'lint'
Requires-Dist: isort ; extra == 'lint'
Requires-Dist: flake8 ; extra == 'lint'
Requires-Dist: flake8-black ; extra == 'lint'
Requires-Dist: flake8-isort ; extra == 'lint'
Requires-Dist: flake8-commas ; extra == 'lint'
Provides-Extra: test
Requires-Dist: pytest ; extra == 'test'
Requires-Dist: pytest-testinfra ; extra == 'test'
